vpos/__init__.py
vpos/api.py
vpos/apps.py
vpos/configs.py
vpos/exceptions.py
vpos/signals.py
vpos/transactions.py
vpos/urls.py
vpos/utils.py
vpos/validators.py
vpos/views.py
vpos/migrations/0001_initial.py
vpos/migrations/0002_alter_transaction_data.py
vpos/migrations/__init__.py
vpos/models/__init__.py
vpos/models/transaction.py
django_vpos-0.1.4.dist-info/LICENCE
django_vpos-0.1.4.dist-info/METADATA
django_vpos-0.1.4.dist-info/WHEEL
django_vpos-0.1.4.dist-info/top_level.txt
django_vpos-0.1.4.dist-info/RECORD
